pyerrors/__init__.py
pyerrors/correlators.py
pyerrors/covobs.py
pyerrors/dirac.py
pyerrors/fits.py
pyerrors/integrate.py
pyerrors/linalg.py
pyerrors/misc.py
pyerrors/mpm.py
pyerrors/obs.py
pyerrors/roots.py
pyerrors/special.py
pyerrors/version.py
pyerrors/input/__init__.py
pyerrors/input/bdio.py
pyerrors/input/dobs.py
pyerrors/input/hadrons.py
pyerrors/input/json.py
pyerrors/input/misc.py
pyerrors/input/openQCD.py
pyerrors/input/pandas.py
pyerrors/input/sfcf.py
pyerrors/input/utils.py
pyerrors-2.15.1.dist-info/licenses/LICENSE
pyerrors-2.15.1.dist-info/METADATA
pyerrors-2.15.1.dist-info/WHEEL
pyerrors-2.15.1.dist-info/top_level.txt
pyerrors-2.15.1.dist-info/RECORD
