Metadata-Version: 2.4
Name: pyerrors
Version: 2.15.1
Summary: Error propagation and statistical analysis for Monte Carlo simulations
Home-page: https://github.com/fjosw/pyerrors
Author: Fabian Joswig
Author-email: fabian.joswig@ed.ac.uk
License: MIT
Project-URL: Documentation, https://fjosw.github.io/pyerrors/pyerrors.html
Project-URL: Bug Tracker, https://github.com/fjosw/pyerrors/issues
Project-URL: Changelog, https://github.com/fjosw/pyerrors/blob/master/CHANGELOG.md
Classifier: Development Status :: 5 - Production/Stable
Classifier: Intended Audience :: Science/Research
Classifier: Programming Language :: Python :: 3
Classifier: Programming Language :: Python :: 3.9
Classifier: Programming Language :: Python :: 3.10
Classifier: Programming Language :: Python :: 3.11
Classifier: Programming Language :: Python :: 3.12
Classifier: Programming Language :: Python :: 3.13
Classifier: Topic :: Scientific/Engineering :: Physics
Requires-Python: >=3.9.0
License-File: LICENSE
Requires-Dist: numpy>=2.0
Requires-Dist: autograd>=1.7.0
Requires-Dist: numdifftools>=0.9.41
Requires-Dist: matplotlib>=3.9
Requires-Dist: scipy>=1.13
Requires-Dist: iminuit>=2.28
Requires-Dist: h5py>=3.11
Requires-Dist: lxml>=5.0
Requires-Dist: python-rapidjson>=1.20
Requires-Dist: pandas>=2.2
Provides-Extra: test
Requires-Dist: pytest; extra == "test"
Requires-Dist: pytest-cov; extra == "test"
Requires-Dist: pytest-benchmark; extra == "test"
Requires-Dist: hypothesis; extra == "test"
Requires-Dist: nbmake; extra == "test"
Requires-Dist: flake8; extra == "test"
Dynamic: author
Dynamic: author-email
Dynamic: classifier
Dynamic: description
Dynamic: description-content-type
Dynamic: home-page
Dynamic: license
Dynamic: license-file
Dynamic: project-url
Dynamic: provides-extra
Dynamic: requires-dist
Dynamic: requires-python
Dynamic: summary
